core_evals/livecodebench/__init__.py
core_evals/livecodebench/framework.yml
core_evals/livecodebench/framework_entrypoint.py
core_evals/livecodebench/output.py
livecodebench/__init__.py
livecodebench/lm_styles.py
livecodebench/benchmarks/__init__.py
livecodebench/benchmarks/code_execution.py
livecodebench/benchmarks/code_generation.py
livecodebench/benchmarks/test_output_prediction.py
livecodebench/benchmarks/utils.py
livecodebench/evaluation/__init__.py
livecodebench/evaluation/compute_code_execution_metrics.py
livecodebench/evaluation/compute_code_generation_metrics.py
livecodebench/evaluation/compute_scores.py
livecodebench/evaluation/compute_test_output_prediction_metrics.py
livecodebench/evaluation/metric.py
livecodebench/evaluation/old_results_check.py
livecodebench/evaluation/pass_k_utils.py
livecodebench/evaluation/testing_util.py
livecodebench/evaluation/utils_execute.py
livecodebench/prompts/__init__.py
livecodebench/prompts/code_execution.py
livecodebench/prompts/code_generation.py
livecodebench/prompts/self_repair.py
livecodebench/prompts/test_output_prediction.py
livecodebench/prompts/few_shot_examples/generation/func.json
livecodebench/prompts/few_shot_examples/generation/stdin.json
livecodebench/runner/__init__.py
livecodebench/runner/base_runner.py
livecodebench/runner/claude3_runner.py
livecodebench/runner/claude_runner.py
livecodebench/runner/cohere_runner.py
livecodebench/runner/custom_evaluator.py
livecodebench/runner/deepseek_runner.py
livecodebench/runner/gemini_runner.py
livecodebench/runner/generic_oai_server_runner.py
livecodebench/runner/main.py
livecodebench/runner/mistral_runner.py
livecodebench/runner/oai_runner.py
livecodebench/runner/parser.py
livecodebench/runner/runner_utils.py
livecodebench/runner/scenario_router.py
livecodebench/runner/vllm_runner.py
livecodebench/utils/__init__.py
livecodebench/utils/extraction_utils.py
livecodebench/utils/multiprocess.py
livecodebench/utils/path_utils.py
livecodebench/utils/scenarios.py
nvidia_livecodebench-25.11.dist-info/METADATA
nvidia_livecodebench-25.11.dist-info/WHEEL
nvidia_livecodebench-25.11.dist-info/entry_points.txt
nvidia_livecodebench-25.11.dist-info/licenses/LICENSE
nvidia_livecodebench-25.11.dist-info/RECORD
