Metadata-Version: 2.4
Name: nvidia-livecodebench
Version: 25.11
Summary: LiveCodeBench - packaged by NVIDIA
Project-URL: Original Project, https://github.com/LiveCodeBench/LiveCodeBench
Project-URL: Paper, https://arxiv.org/abs/2403.07974
Project-URL: Homepage, https://livecodebench.github.io
Author: NVIDIA, LiveCodeBench
License: MIT License
License-File: LICENSE
Classifier: Development Status :: 5 - Production/Stable
Classifier: License :: OSI Approved :: MIT License
Classifier: Operating System :: OS Independent
Classifier: Programming Language :: Python :: 3
Requires-Python: >=3.10
Requires-Dist: annotated-types>=0.7.0
Requires-Dist: anthropic>=0.42.0
Requires-Dist: cohere>=5.13.6
Requires-Dist: datasets>=3.2.0
Requires-Dist: google-genai>=0.6.0
Requires-Dist: jinja2>=3.1.5
Requires-Dist: mistralai==0.4.2
Requires-Dist: nemo-evaluator
Requires-Dist: openai>=1.59.6
Requires-Dist: pebble>=5.1.0
Requires-Dist: tenacity>=9.0.0
